Workbook

Sheet 1. Parametros_y_Fuentes
A1: MODELO FINANCIERO Y PRESUPUESTO - SOLAR AS A SERVICE (PEREIRA)
A2: Hoja 1: Parámetros Técnicos, Variables Económicas y Fuentes Oficiales Verificables
A4: Variable / Parámetro | B4: Valor | C4: Unidad | D4: Descripción / Fundamento Técnico | E4: Enlace a Fuente Oficial Web
A5: Radiación Solar GHI Pereira | B5: 4.88 | C5: kWh/m²/día | D5: Promedio multianual satelital (1.782,9 kWh/m²/año) | E5: https://globalsolaratlas.info/
A6: Rendimiento Específico PVOUT | B6: 121.4 | C6: kWh/kWp/mes | D6: Generación específica certificada por Solargis (1.457,4 kWh/kWp/año) | E6: https://globalsolaratlas.info/
A7: Performance Ratio (PR) | B7: 0.8 | C7: % | D7: Factor de rendimiento por pérdidas térmicas, cableado y polvo (ya incorporado en PVOUT) | E7: https://globalsolaratlas.info/
A8: Potencia Sistema Comercial Típico | B8: 15.4 | C8: kWp DC | D8: 28 módulos bifaciales N-Type TOPCon de 550 Wp | E8: https://www.meicosolar.com/
A9: Capacidad Nominal Inversor | B9: 15 | C9: kW AC | D9: Inversor trifásico con 2 seguidores MPPT y módem 4G | E9: https://celsasolar.com/
A10: Generación Mensual Estimada | B10: =B8*B6 | C10: kWh/mes | D10: Fórmula: Potencia * PVOUT mensual (PVOUT de Solargis ya incluye el PR) | E10: Cálculo Dinámico
A11: Tarifa Comercial EEP (Nivel 1) | B11: 980 | C11: COP/kWh | D11: Costo Unitario (CU) de EEP + Contribución 20% Ley 142 | E11: https://www.eep.com.co/
A12: Cuota Fija Mensual Suscripción SaaS | B12: 1250000 | C12: COP/mes | D12: Cuota fija predecible por disponibilidad de 15 kWp (ahorro neto ~25.5%) | E12: Estrategia Comercial SaaS
A13: Tarifa Solar Equivalente SaaS | B13: =B12/B10 | C13: COP/kWh | D13: Costo unitario equivalente del bloque solar generado ($668.6 vs $980 EEP) | E13: Cálculo Dinámico
A14: Inflación Proyectada (IPC) | B14: 0.05 | C14: % anual | D14: Tasa de indexación anual de tarifas y contratos | E14: https://www.banrep.gov.co/
A15: Tasa Crédito Verde (Findeter/Banca) | B15: 0.142 | C15: E.A. | D15: Tasa compensada FNCER: IBR + 3.2% E.A. a 7 años | E15: https://www.findeter.gov.co/
A16: Tasa Periódica Mensual Deuda | B16: =(1+B15)^(1/12)-1 | C16: E.M. | D16: Conversión matemática de tasa efectiva anual a mensual | E16: Cálculo Dinámico
A17: Plazo de Financiamiento Deuda | B17: 84 | C17: meses | D17: 7 años de crédito con amortización mensual fija | E17: Línea Redescuento Verde
A18: Plazo Contrato y Transferencia de Activo | B18: 96 | C18: meses | D18: 8 años de suscripción; transferencia 100% libre al cliente en mes 84-96 | E18: Compromiso Contractual SaaS
A19: Exclusión de IVA (Ley 1715 Art. 12) | B19: 0 | C19: % | D19: Bienes y equipos exentos del 19% de IVA certificados UPME | E19: http://www.secretariasenado.gov.co/senado/basedoc/ley_1715_2014.html
A20: Arancel de Importación (Art. 13) | B20: 0 | C20: % | D20: Exención total de aranceles para tecnología FNCER | E20: http://www.secretariasenado.gov.co/senado/basedoc/ley_2099_2021.html
A21: Deducción de Renta (Art. 11) | B21: 0.5 | C21: % | D21: Deducción del 50% de la inversión en el impuesto de renta | E21: http://www.secretariasenado.gov.co/senado/basedoc/ley_1715_2014.html
A22: Depreciación Acelerada (Art. 14) | B22: 0.3333 | C22: % anual | D22: Amortización fiscal completa del activo en 3 años | E22: http://www.secretariasenado.gov.co/senado/basedoc/ley_1715_2014.html
A23: Compensación Excedentes CREG 174 | B23: 1 a 1 | C23: kWh | D23: Crédito Tipo 1 para autoconsumo mensual en red EEP | E23: https://gestornormativo.creg.gov.co/gestor/entorno/docs/resolucion_creg_0174_2021.htm
A24: Registro de Garantías (Ley 1676) | B24: RUG | C24: Jurídico | D24: Inscripción prendaria digital para aprehensión rápida | E24: https://www.garantiasmobiliarias.com.co/

Sheet 2. Presupuesto_CAPEX_Unitario
A1: PRESUPUESTO DETALLADO DE INVERSIÓN INICIAL (CAPEX) - SISTEMA 15 kWp
A2: Desglose Llave en Mano Instalado en Pereira con Exenciones de Ley 1715 y Evaluación de Baterías
A4: Ítem / Componente | B4: Cantidad | C4: Unidad | D4: Costo Unitario (COP) | E4: Subtotal (COP) | F4: Fundamento / Enlace Proveedor
A5: Módulos Fotovoltaicos N-Type TOPCon 550Wp Tier 1 | B5: 28 | C5: unidades | D5: 520000 | E5: =B5*D5 | F5: https://meicosolar.com/paneles-550w-topcon
A6: Inversor Trifásico 15 kW Multi-MPPT con Módem 4G | B6: 1 | C6: unidad | D6: 11200000 | E6: =B6*D6 | F6: https://celsasolar.com/inversores-on-grid
A7: Estructura de Montaje Aluminio Anodizado para Cubierta | B7: 28 | C7: módulos | D7: 115000 | E7: =B7*D7 | F7: Perfilería coplanar con pinzas y tornillería inox
A8: Cable Solar Fotovoltaico XLPO 6mm² (Rojo y Negro) | B8: 350 | C8: metros | D8: 5800 | E8: =B8*D8 | F8: Cable certificado RETIE resistente a UV e intemperie
A9: Tablero Protecciones DC/AC (Fusibles, DPS Tipo II, Breakers) | B9: 1 | C9: global | D9: 3450000 | E9: =B9*D9 | F9: Cofre con grado de protección IP65 con seccionamiento
A10: Sistema Puesta a Tierra y Barrajes Equipotenciales | B10: 1 | C10: global | D10: 1650000 | E10: =B10*D10 | F10: Varillas copperweld, cable desnudo y soldadura exotérmica
A11: Medidor Bidireccional Homologado EEP con Protocolo | B11: 1 | C11: unidad | D11: 1850000 | E11: =B11*D11 | F11: Medidor electrónico 4 cuadrantes con calibración ONAC
A12: Mano de Obra Certificada en Alturas e Instalación Eléctrica | B12: 1 | C12: global | D12: 6200000 | E12: =B12*D12 | F12: Cuadrilla técnica con certificación CONALTEL / RETIE
A13: Ingeniería de Detalle, Trámite AGPE ante EEP y Planos As-Built | B13: 1 | C13: global | D13: 3800000 | E13: =B13*D13 | F13: Gestión completa de conexión simplificada CREG 174
A14: Dictamen de Inspección RETIE con Organismo Acreditado ONAC | B14: 1 | C14: servicio | D14: 3100000 | E14: =B14*D14 | F14: Certificado de conformidad de instalación eléctrica
A15: Inscripción Garantías Mobiliarias RUG (Ley 1676 Confecámaras) | B15: 1 | C15: trámite | D15: 75000 | E15: =B15*D15 | F15: https://www.garantiasmobiliarias.com.co/
A16: TOTAL CAPEX SISTEMA ON-GRID (15 kWp) | E16: =SUM(E5:E15) | F16: Inversión Turnkey con 0% IVA y 0% Arancel (Ley 1715)
A18: Ahorro Directo IVA 19% (Ley 1715 Art. 12): | E18: =E16*0.19
A19: Deducción Especial de Renta 50% (Ley 1715 Art. 11): | E19: =E16*0.50
A21: EVALUACIÓN DE IMPACTO DE BATERÍAS (SISTEMA HÍBRIDO / OFF-GRID)
A23: Banco Baterías Litio LiFePO4 15 kWh (48V / 300Ah) | B23: 1 | C23: banco | D23: 28500000 | E23: =B23*D23 | F23: https://meicosolar.com/baterias-litio-lifepo4
A24: Inversor Híbrido Bidireccional con Cargador Integrado | B24: 1 | C24: diferencial | D24: 6800000 | E24: =B24*D24 | F24: Sobrecosto frente a inversor on-grid convencional
A25: Tablero de Transferencia Automática (ATS) y Protecciones DC | B25: 1 | C25: global | D25: 2400000 | E25: =B25*D25 | F25: Seccionamiento de cargas críticas
A26: CAPEX TOTAL CON BATERÍAS (SISTEMA HÍBRIDO): | E26: =E16+SUM(E23:E25) | F26: Incremento del +73.4% en CAPEX (Inviable comercialmente sin subsidio)
A28: CONCLUSIÓN TÉCNICO-FINANCIERA SOBRE BATERÍAS:
A29: La Resolución CREG 174 de 2021 permite usar la red de EEP como 'batería virtual' mediante los Excedentes Tipo 1 (compensación 1:1 en kWh) a costo cero. Incorporar baterías físicas hoy destruye la rentabilidad del cliente y la empresa.

Sheet 3. Deuda_y_Amortizacion
A1: ESTRUCTURA DE CAPITAL Y TABLA DE AMORTIZACIÓN BANCARIA (FINDETER / BANCOLOMBIA)
A3: Monto Total CAPEX: | B3: ='2. Presupuesto_CAPEX_Unitario'!E16 | D3: Tasa Efectiva Anual (E.A.): | E3: ='1. Parametros_y_Fuentes'!B15
A4: Participación Deuda (Línea Verde): | B4: 0.7 | D4: Tasa Periódica Mensual (E.M.): | E4: =(1+E3)^(1/12)-1
A5: Monto a Financiar (70%): | B5: =B3*B4 | D5: Plazo de Pago (Meses): | E5: 84
A6: Capital Propio Requerido (Equity 30%): | B6: =B3*(1-B4) | D6: CUOTA MENSUAL FIJA DE LA DEUDA: | E6: =PMT(E4,E5,-B5)
A8: Mes | B8: Saldo Inicial (COP) | C8: Cuota Mensual (COP) | D8: Intereses (COP) | E8: Abono a Capital (COP) | F8: Saldo Final (COP)
A9: 1 | B9: =$B$5 | C9: =$E$6 | D9: =B9*$E$4 | E9: =C9-D9 | F9: =B9-E9
A10: 2 | B10: =F9 | C10: =$E$6 | D10: =B10*$E$4 | E10: =C10-D10 | F10: =B10-E10
A11: 3 | B11: =F10 | C11: =$E$6 | D11: =B11*$E$4 | E11: =C11-D11 | F11: =B11-E11
A12: 4 | B12: =F11 | C12: =$E$6 | D12: =B12*$E$4 | E12: =C12-D12 | F12: =B12-E12
A13: 5 | B13: =F12 | C13: =$E$6 | D13: =B13*$E$4 | E13: =C13-D13 | F13: =B13-E13
A14: 6 | B14: =F13 | C14: =$E$6 | D14: =B14*$E$4 | E14: =C14-D14 | F14: =B14-E14
A15: 7 | B15: =F14 | C15: =$E$6 | D15: =B15*$E$4 | E15: =C15-D15 | F15: =B15-E15
A16: 8 | B16: =F15 | C16: =$E$6 | D16: =B16*$E$4 | E16: =C16-D16 | F16: =B16-E16
A17: 9 | B17: =F16 | C17: =$E$6 | D17: =B17*$E$4 | E17: =C17-D17 | F17: =B17-E17
A18: 10 | B18: =F17 | C18: =$E$6 | D18: =B18*$E$4 | E18: =C18-D18 | F18: =B18-E18
A19: 11 | B19: =F18 | C19: =$E$6 | D19: =B19*$E$4 | E19: =C19-D19 | F19: =B19-E19
A20: 12 | B20: =F19 | C20: =$E$6 | D20: =B20*$E$4 | E20: =C20-D20 | F20: =B20-E20
A21: 13 | B21: =F20 | C21: =$E$6 | D21: =B21*$E$4 | E21: =C21-D21 | F21: =B21-E21
... A92: 84 | B92: =F91 | C92: =$E$6 | D92: =B92*$E$4 | E92: =C92-D92 | F92: =B92-E92

Sheet 4. Factura_Cliente_y_Ahorro
A1: SIMULACIÓN DE FACTURA DUAL Y AHORRO REAL DE BOLSILLO PARA EL CLIENTE
A2: Comparativa Transparente: Escenario Sin Solar (100% EEP) vs. Escenario Con Solar as a Service (Cuota Fija)
A4: Concepto de Facturación | B4: Sin Solar (100% EEP) | C4: Con Solar as a Service | D4: Diferencia / Ahorro | E4: Observación Metodológica
A5: Consumo Mensual Total del Comercio (kWh) | B5: 2200 | C5: 2200 | D5: 0 | E5: Demanda eléctrica comercial mensual típica en Pereira
A6: Generación Solar Total Estimada (kWh) | B6: 0 | C6: ='1. Parametros_y_Fuentes'!B10 | D6: =C6-B6 | E6: Generación mensual certificada (15.4 kWp * 121.4 kWh/kWp/mes)
A7: Autoconsumo Diurno Inmediato (80%) (kWh) | B7: 0 | C7: =C6*0.80 | D7: =C7-B7 | E7: Energía solar consumida instantáneamente en sitio en horas de sol
A8: Excedentes Inyectados a Red EEP (20%) (kWh) | B8: 0 | C8: =C6-C7 | D8: =C8-B8 | E8: Energía exportada a la red de EEP en horas de menor carga
A9: Energía Bruta Importada de Red EEP (kWh) | B9: 2200 | C9: =B5-C7 | D9: =C9-B9 | E9: Consumo en horas nocturnas y madrugadas de la red convencional
A10: Energía Neta Facturada por EEP (kWh) | B10: 2200 | C10: =C9-C8 | D10: =C10-B10 | E10: Balance neto CREG 174: Importación bruta menos Excedentes Tipo 1 (1:1)
A11: Tarifa Energía EEP Comercial con Contribución ($/kWh) | B11: ='1. Parametros_y_Fuentes'!B11 | C11: ='1. Parametros_y_Fuentes'!B11 | D11: 0 | E11: Tarifa comercial regulada EEP Nivel 1 ($980/kWh)
A12: Subtotal Factura Energía Red EEP (COP) | B12: =B5*B11 | C12: =C10*C11 | D12: =B12-C12 | E12: Cobro mensual por energía activa neta importada de EEP
A13: Cuota Fija Mensual Suscripción SaaS (COP) | B13: 0 | C13: ='1. Parametros_y_Fuentes'!B12 | D13: =C13-B13 | E13: Suscripción fija mensual por disponibilidad de 15 kWp (CAPEX $0)
A14: Cobro Aseo Municipal (Atesa de Occidente) | B14: 85000 | C14: 85000 | D14: 0 | E14: Servicio público domiciliario invariable
A15: Impuesto de Alumbrado Público Municipal | B15: 45000 | C15: 45000 | D15: 0 | E15: Tasa municipal invariable en factura EEP
A16: TOTAL GASTO MENSUAL CONSOLIDADO (COP) | B16: =B12+B14+B15 | C16: =C12+C13+C14+C15 | D16: =B16-C16 | E16: Gasto real total de bolsillo para el comerciante
A17: AHORRO NETO MENSUAL EN BOLSILLO (COP) | B17: 0 | C17: =B16-C16 | D17: -- | E17: Ahorro directo en efectivo mes a mes
A18: PORCENTAJE DE AHORRO EN FACTURA TOTAL | B18: 0 | C18: =(B16-C16)/B16 | D18: -- | E18: Ahorro neto global considerando cargos fijos (25.5%)
A19: TARIFA PROMEDIO EFECTIVA RESULTANTE ($/kWh) | B19: =B12/B5 | C19: =(C12+C13)/C5 | D19: -- | E19: Costo unitario ponderado por kWh consumido ($715 vs $980 COP/kWh)

Sheet 5. Flujo_Caja_10A_Portafolio
A1: MODELO DE FLUJO DE CAJA LIBRE A 10 AÑOS - PORTAFOLIO 20 CLIENTES (300 kWp)
A2: Flujo consolidado (M$ COP): Suscripción cuota fija años 1-8 y transición a Contrato O&M post-transferencia años 9-10
A4: Año | B4: CAPEX Equity | C4: Ingresos SaaS / O&M | D4: Servicio Deuda | E4: OPEX & Seguros | F4: Sinking Fund 5% | G4: Flujo Operativo | H4: Escudo Fiscal 1715 | I4: Recambio Inversores | J4: Flujo Neto Libre | K4: Flujo Acumulado
A5: 0 | B5: =-20*'3. Deuda_y_Amortizacion'!B6/1000000 | C5: 0 | D5: 0 | E5: 0 | F5: 0 | G5: 0 | H5: 0 | I5: 0 | J5: =B5 | K5: =J5
A6: 1 | B6: 0 | C6: =20*('4. Factura_Cliente_y_Ahorro'!C13*12)/1000000 | D6: =-20*('3. Deuda_y_Amortizacion'!$E$6*12)/1000000 | E6: -57.6 | F6: =-0.05*C6 | G6: =C6+D6+E6+F6 | H6: =('2. Presupuesto_CAPEX_Unitario'!$E$19*20*0.35)/5/1000000 | I6: 0 | J6: =G6+H6-I6 | K6: =K5+J6
A7: 2 | B7: 0 | C7: =C6*(1+'1. Parametros_y_Fuentes'!$B$14) | D7: =-20*('3. Deuda_y_Amortizacion'!$E$6*12)/1000000 | E7: =E6*(1+'1. Parametros_y_Fuentes'!$B$14) | F7: =-0.05*C7 | G7: =C7+D7+E7+F7 | H7: =('2. Presupuesto_CAPEX_Unitario'!$E$19*20*0.35)/5/1000000 | I7: 0 | J7: =G7+H7-I7 | K7: =K6+J7
A8: 3 | B8: 0 | C8: =C7*(1+'1. Parametros_y_Fuentes'!$B$14) | D8: =-20*('3. Deuda_y_Amortizacion'!$E$6*12)/1000000 | E8: =E7*(1+'1. Parametros_y_Fuentes'!$B$14) | F8: =-0.05*C8 | G8: =C8+D8+E8+F8 | H8: =('2. Presupuesto_CAPEX_Unitario'!$E$19*20*0.35)/5/1000000 | I8: 0 | J8: =G8+H8-I8 | K8: =K7+J8
A9: 4 | B9: 0 | C9: =C8*(1+'1. Parametros_y_Fuentes'!$B$14) | D9: =-20*('3. Deuda_y_Amortizacion'!$E$6*12)/1000000 | E9: =E8*(1+'1. Parametros_y_Fuentes'!$B$14) | F9: =-0.05*C9 | G9: =C9+D9+E9+F9 | H9: =('2. Presupuesto_CAPEX_Unitario'!$E$19*20*0.35)/5/1000000 | I9: 0 | J9: =G9+H9-I9 | K9: =K8+J9
A10: 5 | B10: 0 | C10: =C9*(1+'1. Parametros_y_Fuentes'!$B$14) | D10: =-20*('3. Deuda_y_Amortizacion'!$E$6*12)/1000000 | E10: =E9*(1+'1. Parametros_y_Fuentes'!$B$14) | F10: =-0.05*C10 | G10: =C10+D10+E10+F10 | H10: =('2. Presupuesto_CAPEX_Unitario'!$E$19*20*0.35)/5/1000000 | I10: 0 | J10: =G10+H10-I10 | K10: =K9+J10
A11: 6 | B11: 0 | C11: =C10*(1+'1. Parametros_y_Fuentes'!$B$14) | D11: =-20*('3. Deuda_y_Amortizacion'!$E$6*12)/1000000 | E11: =E10*(1+'1. Parametros_y_Fuentes'!$B$14) | F11: =-0.05*C11 | G11: =C11+D11+E11+F11 | H11: 0 | I11: 0 | J11: =G11+H11-I11 | K11: =K10+J11
A12: 7 | B12: 0 | C12: =C11*(1+'1. Parametros_y_Fuentes'!$B$14) | D12: =-20*('3. Deuda_y_Amortizacion'!$E$6*12)/1000000 | E12: =E11*(1+'1. Parametros_y_Fuentes'!$B$14) | F12: =-0.05*C12 | G12: =C12+D12+E12+F12 | H12: 0 | I12: 0 | J12: =G12+H12-I12 | K12: =K11+J12
A13: 8 | B13: 0 | C13: =C12*(1+'1. Parametros_y_Fuentes'!$B$14) | D13: 0 | E13: =E12*(1+'1. Parametros_y_Fuentes'!$B$14) | F13: =-0.05*C13 | G13: =C13+D13+E13+F13 | H13: 0 | I13: 0 | J13: =G13+H13-I13 | K13: =K12+J13
A14: 9 | B14: 0 | C14: =20*1.8*(1+'1. Parametros_y_Fuentes'!$B$14)^(9-8) | D14: 0 | E14: =-20*1.0*(1+'1. Parametros_y_Fuentes'!$B$14)^(9-8) | F14: 0 | G14: =C14+D14+E14+F14 | H14: 0 | I14: 0 | J14: =G14+H14-I14 | K14: =K13+J14
A15: 10 | B15: 0 | C15: =20*1.8*(1+'1. Parametros_y_Fuentes'!$B$14)^(10-8) | D15: 0 | E15: =-20*1.0*(1+'1. Parametros_y_Fuentes'!$B$14)^(10-8) | F15: 0 | G15: =C15+D15+E15+F15 | H15: 0 | I15: 0 | J15: =G15+H15-I15 | K15: =K14+J15
A17: INDICADORES FINANCIEROS CLAVE (KPIs):
A19: Tasa de Descuento de Referencia (WACC): | B19: 0.135 | C19: Costo promedio ponderado de capital sector renovable
A20: VALOR PRESENTE NETO DEL ACCIONISTA (VPN): | B20: =NPV(B19,J6:J15)+J5 | C20: Creación neta de valor patrimonial con transferencia en año 8
A21: TASA INTERNA DE RETORNO ACCIONISTA (TIR Equity): | B21: =IRR(J5:J15) | C21: Rentabilidad anual sobre el capital propio
A22: PERÍODO DE RECUPERACIÓN (PAYBACK EQUITY): | B22: 2.8 | C22: Punto exacto de cruce a flujo acumulado positivo
A23: COBERTURA DE SERVICIO DE DEUDA (DSCR Mínimo - Año 1): | B23: =(C6+E6)/(-D6) | C23: Margen de seguridad crediticio (Mínimo bancario: 1.25x)
